README.md
setup.py
steemconnect/__init__.py
steemconnect/client.py
steemconnect/defaults.py
steemconnect/mixins.py
steemconnect/operations.py
steemconnect/utils.py
steemconnect.egg-info/PKG-INFO
steemconnect.egg-info/SOURCES.txt
steemconnect.egg-info/dependency_links.txt
steemconnect.egg-info/requires.txt
steemconnect.egg-info/top_level.txt