Metadata-Version: 1.0
Name: steemconnect
Version: 0.0.2
Summary: Python client library of SteemConnect
Home-page: https://github.com/emre/steemconnect
Author: Emre Yilmaz
Author-email: mail@emreyilmaz.me
License: MIT
Platform: UNKNOWN
